extracto/__init__.py
extracto/annotate.py
extracto/bannable_product.py
extracto/cache.py
extracto/equals.py
extracto/extract_object.py
extracto/extract_table.py
extracto/infer_table.py
extracto/selectors.py
extracto/utils.py
extracto-0.12.dist-info/LICENSE
extracto-0.12.dist-info/METADATA
extracto-0.12.dist-info/WHEEL
extracto-0.12.dist-info/top_level.txt
extracto-0.12.dist-info/RECORD
