Metadata-Version: 2.1
Name: extracto
Version: 0.12
Summary: Extract Python dicts from HTML files, fast.
Home-page: https://github.com/cldellow/extracto
Author: Colin Dellow
License: Apache License, Version 2.0
Project-URL: Issues, https://github.com/cldellow/extracto/issues
Project-URL: CI, https://github.com/cldellow/extracto/actions
Project-URL: Changelog, https://github.com/cldellow/extracto/releases
Requires-Python: >=3.7
License-File: LICENSE
Requires-Dist: selectolax
Provides-Extra: test
Requires-Dist: pytest ; extra == 'test'
Requires-Dist: pytest-watch ; extra == 'test'
Requires-Dist: wheel ; extra == 'test'
Requires-Dist: pytest-skip-slow ; extra == 'test'
Requires-Dist: pytest-profiling ; extra == 'test'
Requires-Dist: coverage ; extra == 'test'
